qsmolagents/__init__.py
qsmolagents/_function_type_hints_utils.py
qsmolagents/agent_types.py
qsmolagents/agents.py
qsmolagents/cli.py
qsmolagents/default_tools.py
qsmolagents/e2b_executor.py
qsmolagents/gradio_ui.py
qsmolagents/local_python_executor.py
qsmolagents/memory.py
qsmolagents/models.py
qsmolagents/monitoring.py
qsmolagents/remote_executors.py
qsmolagents/tool_validation.py
qsmolagents/tools.py
qsmolagents/utils.py
qsmolagents/vision_web_browser.py
qsmolagents/web_agent.py
qsmolagents/prompts/__init__.py
qsmolagents/prompts/code_agent.yaml
qsmolagents/prompts/toolcalling_agent.yaml
qsmolagents/scripts/build_dom_tree.js
qsmolagents/scripts/convert_dom_to_markdown.js
qsmolagents-1.10.1.dev8.dist-info/LICENSE
qsmolagents-1.10.1.dev8.dist-info/METADATA
qsmolagents-1.10.1.dev8.dist-info/WHEEL
qsmolagents-1.10.1.dev8.dist-info/entry_points.txt
qsmolagents-1.10.1.dev8.dist-info/top_level.txt
qsmolagents-1.10.1.dev8.dist-info/RECORD
