Metadata-Version: 2.2
Name: qsmolagents
Version: 1.10.1.dev8
Summary: qsmolagents
Author: Thomas Wolf
Author-email: Aymeric Roucher <aymeric@hf.co>
License: Apache-2.0
Requires-Python: >=3.10
License-File: LICENSE
Requires-Dist: huggingface-hub>=0.28.0
Requires-Dist: requests>=2.32.3
Requires-Dist: rich>=13.9.4
Requires-Dist: pandas>=2.2.3
Requires-Dist: jinja2>=3.1.4
Requires-Dist: pillow>=11.0.0
Requires-Dist: markdownify>=0.14.1
Requires-Dist: duckduckgo-search>=6.3.7
Requires-Dist: python-dotenv
Provides-Extra: torch
Requires-Dist: torch; extra == "torch"
Requires-Dist: torchvision; extra == "torch"
Provides-Extra: audio
Requires-Dist: soundfile; extra == "audio"
Requires-Dist: qsmolagents[torch]; extra == "audio"
Provides-Extra: docker
Requires-Dist: docker; extra == "docker"
Requires-Dist: python-dotenv>=1.0.1; extra == "docker"
Provides-Extra: e2b
Requires-Dist: e2b-code-interpreter>=1.0.3; extra == "e2b"
Requires-Dist: python-dotenv>=1.0.1; extra == "e2b"
Provides-Extra: gradio
Requires-Dist: gradio>=5.13.2; extra == "gradio"
Provides-Extra: litellm
Requires-Dist: litellm>=1.61.7; extra == "litellm"
Provides-Extra: mcp
Requires-Dist: mcpadapt>=0.0.6; extra == "mcp"
Requires-Dist: mcp; extra == "mcp"
Provides-Extra: mlx-lm
Requires-Dist: mlx-lm; extra == "mlx-lm"
Provides-Extra: openai
Requires-Dist: openai>=1.58.1; extra == "openai"
Provides-Extra: telemetry
Requires-Dist: arize-phoenix; extra == "telemetry"
Requires-Dist: opentelemetry-sdk; extra == "telemetry"
Requires-Dist: opentelemetry-exporter-otlp; extra == "telemetry"
Requires-Dist: openinference-instrumentation-smolagents>=0.1.4; extra == "telemetry"
Provides-Extra: transformers
Requires-Dist: accelerate; extra == "transformers"
Requires-Dist: transformers<4.49.0,>=4.0.0; extra == "transformers"
Requires-Dist: qsmolagents[torch]; extra == "transformers"
Provides-Extra: all
Requires-Dist: qsmolagents[audio,e2b,gradio,litellm,mcp,openai,telemetry,transformers]; extra == "all"
Provides-Extra: quality
Requires-Dist: ruff>=0.9.0; extra == "quality"
Provides-Extra: test
Requires-Dist: ipython>=8.31.0; extra == "test"
Requires-Dist: pytest>=8.1.0; extra == "test"
Requires-Dist: python-dotenv>=1.0.1; extra == "test"
Requires-Dist: qsmolagents[all]; extra == "test"
Requires-Dist: rank-bm25; extra == "test"
Provides-Extra: dev
Requires-Dist: qsmolagents[quality,test]; extra == "dev"
Requires-Dist: sqlalchemy; extra == "dev"
